{
  "metadata": {
    "source_file": "data\\raw\\txt\\mtsamples\\mtsamples_4957__autopsy___7_.txt",
    "file_name": "mtsamples_4957__autopsy___7_.txt",
    "file_type": ".txt",
    "file_size_bytes": 10765,
    "processed_at": "2026-05-09T09:54:48.154405"
  },
  "entities": [
    {
      "text": "clad",
      "label": "CHEMICAL",
      "start_char": 12,
      "end_char": 16,
      "sentence_idx": 1,
      "concept_id": "UNKNOWN",
      "concept_name": "clad",
      "kb_source": "rxnorm",
      "link_score": 0.0,
      "timestamp": null
    },
    {
      "text": "teeth",
      "label": "DISEASE",
      "start_char": 4,
      "end_char": 9,
      "sentence_idx": 14,
      "concept_id": "UNKNOWN",
      "concept_name": "teeth",
      "kb_source": "mesh",
      "link_score": 0.0,
      "timestamp": null
    },
    {
      "text": "trauma",
      "label": "DISEASE",
      "start_char": 35,
      "end_char": 41,
      "sentence_idx": 15,
      "concept_id": "UNKNOWN",
      "concept_name": "trauma",
      "kb_source": "mesh",
      "link_score": 0.0,
      "timestamp": null
    },
    {
      "text": "breasts",
      "label": "DISEASE",
      "start_char": 4,
      "end_char": 11,
      "sentence_idx": 19,
      "concept_id": "UNKNOWN",
      "concept_name": "breasts",
      "kb_source": "mesh",
      "link_score": 0.0,
      "timestamp": null
    },
    {
      "text": "anus",
      "label": "DISEASE",
      "start_char": 4,
      "end_char": 8,
      "sentence_idx": 29,
      "concept_id": "UNKNOWN",
      "concept_name": "anus",
      "kb_source": "mesh",
      "link_score": 0.0,
      "timestamp": null
    },
    {
      "text": "upper extremities",
      "label": "DISEASE",
      "start_char": 4,
      "end_char": 21,
      "sentence_idx": 33,
      "concept_id": "UNKNOWN",
      "concept_name": "upper extremities",
      "kb_source": "mesh",
      "link_score": 0.0,
      "timestamp": null
    },
    {
      "text": "flexion contractures",
      "label": "DISEASE",
      "start_char": 27,
      "end_char": 47,
      "sentence_idx": 33,
      "concept_id": "UNKNOWN",
      "concept_name": "flexion contractures",
      "kb_source": "mesh",
      "link_score": 0.0,
      "timestamp": null
    },
    {
      "text": "striae",
      "label": "DISEASE",
      "start_char": 53,
      "end_char": 59,
      "sentence_idx": 33,
      "concept_id": "UNKNOWN",
      "concept_name": "striae",
      "kb_source": "mesh",
      "link_score": 0.0,
      "timestamp": null
    },
    {
      "text": "thoracic kyphosis",
      "label": "DISEASE",
      "start_char": 26,
      "end_char": 43,
      "sentence_idx": 38,
      "concept_id": "UNKNOWN",
      "concept_name": "thoracic kyphosis",
      "kb_source": "mesh",
      "link_score": 0.0,
      "timestamp": null
    },
    {
      "text": "osteoporosis",
      "label": "DISEASE",
      "start_char": 16,
      "end_char": 28,
      "sentence_idx": 40,
      "concept_id": "UNKNOWN",
      "concept_name": "osteoporosis",
      "kb_source": "mesh",
      "link_score": 0.0,
      "timestamp": null
    },
    {
      "text": "fracture",
      "label": "DISEASE",
      "start_char": 49,
      "end_char": 57,
      "sentence_idx": 41,
      "concept_id": "UNKNOWN",
      "concept_name": "fracture",
      "kb_source": "mesh",
      "link_score": 0.0,
      "timestamp": null
    },
    {
      "text": "Calculi",
      "label": "DISEASE",
      "start_char": 0,
      "end_char": 7,
      "sentence_idx": 45,
      "concept_id": "UNKNOWN",
      "concept_name": "Calculi",
      "kb_source": "mesh",
      "link_score": 0.0,
      "timestamp": null
    },
    {
      "text": "subgaleal",
      "label": "DISEASE",
      "start_char": 47,
      "end_char": 56,
      "sentence_idx": 50,
      "concept_id": "UNKNOWN",
      "concept_name": "subgaleal",
      "kb_source": "mesh",
      "link_score": 0.0,
      "timestamp": null
    },
    {
      "text": "adhesions",
      "label": "DISEASE",
      "start_char": 29,
      "end_char": 38,
      "sentence_idx": 53,
      "concept_id": "UNKNOWN",
      "concept_name": "adhesions",
      "kb_source": "mesh",
      "link_score": 0.0,
      "timestamp": null
    },
    {
      "text": "trauma",
      "label": "DISEASE",
      "start_char": 17,
      "end_char": 23,
      "sentence_idx": 63,
      "concept_id": "UNKNOWN",
      "concept_name": "trauma",
      "kb_source": "mesh",
      "link_score": 0.0,
      "timestamp": null
    },
    {
      "text": "atherosclerosis",
      "label": "DISEASE",
      "start_char": 29,
      "end_char": 44,
      "sentence_idx": 65,
      "concept_id": "UNKNOWN",
      "concept_name": "atherosclerosis",
      "kb_source": "mesh",
      "link_score": 0.0,
      "timestamp": null
    },
    {
      "text": "atherosclerosis",
      "label": "DISEASE",
      "start_char": 43,
      "end_char": 58,
      "sentence_idx": 66,
      "concept_id": "UNKNOWN",
      "concept_name": "atherosclerosis",
      "kb_source": "mesh",
      "link_score": 0.0,
      "timestamp": null
    },
    {
      "text": "tumors",
      "label": "DISEASE",
      "start_char": 26,
      "end_char": 32,
      "sentence_idx": 70,
      "concept_id": "UNKNOWN",
      "concept_name": "tumors",
      "kb_source": "mesh",
      "link_score": 0.0,
      "timestamp": null
    },
    {
      "text": "cysts",
      "label": "DISEASE",
      "start_char": 34,
      "end_char": 39,
      "sentence_idx": 70,
      "concept_id": "C0010682",
      "concept_name": "L-Cystine",
      "kb_source": "mesh",
      "link_score": 0.7127127051353455,
      "timestamp": null
    },
    {
      "text": "infarcts",
      "label": "DISEASE",
      "start_char": 44,
      "end_char": 52,
      "sentence_idx": 70,
      "concept_id": "UNKNOWN",
      "concept_name": "infarcts",
      "kb_source": "mesh",
      "link_score": 0.0,
      "timestamp": null
    },
    {
      "text": "fibrosis",
      "label": "DISEASE",
      "start_char": 25,
      "end_char": 33,
      "sentence_idx": 81,
      "concept_id": "UNKNOWN",
      "concept_name": "fibrosis",
      "kb_source": "mesh",
      "link_score": 0.0,
      "timestamp": null
    },
    {
      "text": "tumors",
      "label": "DISEASE",
      "start_char": 35,
      "end_char": 41,
      "sentence_idx": 81,
      "concept_id": "UNKNOWN",
      "concept_name": "tumors",
      "kb_source": "mesh",
      "link_score": 0.0,
      "timestamp": null
    },
    {
      "text": "cysts",
      "label": "DISEASE",
      "start_char": 43,
      "end_char": 48,
      "sentence_idx": 81,
      "concept_id": "C0010682",
      "concept_name": "L-Cystine",
      "kb_source": "mesh",
      "link_score": 0.7127127051353455,
      "timestamp": null
    },
    {
      "text": "green-brown stone",
      "label": "DISEASE",
      "start_char": 20,
      "end_char": 37,
      "sentence_idx": 87,
      "concept_id": "UNKNOWN",
      "concept_name": "green-brown stone",
      "kb_source": "mesh",
      "link_score": 0.0,
      "timestamp": null
    },
    {
      "text": "green-brown stone",
      "label": "DISEASE",
      "start_char": 61,
      "end_char": 78,
      "sentence_idx": 88,
      "concept_id": "UNKNOWN",
      "concept_name": "green-brown stone",
      "kb_source": "mesh",
      "link_score": 0.0,
      "timestamp": null
    },
    {
      "text": "ulcerations",
      "label": "DISEASE",
      "start_char": 3,
      "end_char": 14,
      "sentence_idx": 104,
      "concept_id": "UNKNOWN",
      "concept_name": "ulcerations",
      "kb_source": "mesh",
      "link_score": 0.0,
      "timestamp": null
    },
    {
      "text": "petechiae",
      "label": "DISEASE",
      "start_char": 46,
      "end_char": 55,
      "sentence_idx": 105,
      "concept_id": "UNKNOWN",
      "concept_name": "petechiae",
      "kb_source": "mesh",
      "link_score": 0.0,
      "timestamp": null
    },
    {
      "text": "perforations",
      "label": "DISEASE",
      "start_char": 3,
      "end_char": 15,
      "sentence_idx": 108,
      "concept_id": "UNKNOWN",
      "concept_name": "perforations",
      "kb_source": "mesh",
      "link_score": 0.0,
      "timestamp": null
    },
    {
      "text": "esophagus",
      "label": "DISEASE",
      "start_char": 4,
      "end_char": 13,
      "sentence_idx": 109,
      "concept_id": "UNKNOWN",
      "concept_name": "esophagus",
      "kb_source": "mesh",
      "link_score": 0.0,
      "timestamp": null
    },
    {
      "text": "inferior hepatic adhesions",
      "label": "DISEASE",
      "start_char": 19,
      "end_char": 45,
      "sentence_idx": 115,
      "concept_id": "UNKNOWN",
      "concept_name": "inferior hepatic adhesions",
      "kb_source": "mesh",
      "link_score": 0.0,
      "timestamp": null
    },
    {
      "text": "congestion",
      "label": "DISEASE",
      "start_char": 63,
      "end_char": 73,
      "sentence_idx": 117,
      "concept_id": "UNKNOWN",
      "concept_name": "congestion",
      "kb_source": "mesh",
      "link_score": 0.0,
      "timestamp": null
    },
    {
      "text": "fibrosis",
      "label": "DISEASE",
      "start_char": 3,
      "end_char": 11,
      "sentence_idx": 119,
      "concept_id": "UNKNOWN",
      "concept_name": "fibrosis",
      "kb_source": "mesh",
      "link_score": 0.0,
      "timestamp": null
    },
    {
      "text": "cysts",
      "label": "DISEASE",
      "start_char": 13,
      "end_char": 18,
      "sentence_idx": 119,
      "concept_id": "C0010682",
      "concept_name": "L-Cystine",
      "kb_source": "mesh",
      "link_score": 0.7127127051353455,
      "timestamp": null
    },
    {
      "text": "infarcts",
      "label": "DISEASE",
      "start_char": 22,
      "end_char": 30,
      "sentence_idx": 119,
      "concept_id": "UNKNOWN",
      "concept_name": "infarcts",
      "kb_source": "mesh",
      "link_score": 0.0,
      "timestamp": null
    },
    {
      "text": "trauma",
      "label": "DISEASE",
      "start_char": 24,
      "end_char": 30,
      "sentence_idx": 126,
      "concept_id": "UNKNOWN",
      "concept_name": "trauma",
      "kb_source": "mesh",
      "link_score": 0.0,
      "timestamp": null
    },
    {
      "text": "atrophy",
      "label": "DISEASE",
      "start_char": 121,
      "end_char": 128,
      "sentence_idx": 126,
      "concept_id": "UNKNOWN",
      "concept_name": "atrophy",
      "kb_source": "mesh",
      "link_score": 0.0,
      "timestamp": null
    },
    {
      "text": "hemorrhages",
      "label": "DISEASE",
      "start_char": 13,
      "end_char": 24,
      "sentence_idx": 128,
      "concept_id": "UNKNOWN",
      "concept_name": "hemorrhages",
      "kb_source": "mesh",
      "link_score": 0.0,
      "timestamp": null
    },
    {
      "text": "epiglottis",
      "label": "DISEASE",
      "start_char": 66,
      "end_char": 76,
      "sentence_idx": 130,
      "concept_id": "UNKNOWN",
      "concept_name": "epiglottis",
      "kb_source": "mesh",
      "link_score": 0.0,
      "timestamp": null
    },
    {
      "text": "hemorrhages",
      "label": "DISEASE",
      "start_char": 13,
      "end_char": 24,
      "sentence_idx": 137,
      "concept_id": "UNKNOWN",
      "concept_name": "hemorrhages",
      "kb_source": "mesh",
      "link_score": 0.0,
      "timestamp": null
    },
    {
      "text": "trauma",
      "label": "DISEASE",
      "start_char": 35,
      "end_char": 41,
      "sentence_idx": 141,
      "concept_id": "UNKNOWN",
      "concept_name": "trauma",
      "kb_source": "mesh",
      "link_score": 0.0,
      "timestamp": null
    },
    {
      "text": "neuropathology",
      "label": "DISEASE",
      "start_char": 62,
      "end_char": 76,
      "sentence_idx": 142,
      "concept_id": "UNKNOWN",
      "concept_name": "neuropathology",
      "kb_source": "mesh",
      "link_score": 0.0,
      "timestamp": null
    },
    {
      "text": "neuropathology",
      "label": "DISEASE",
      "start_char": 121,
      "end_char": 135,
      "sentence_idx": 142,
      "concept_id": "UNKNOWN",
      "concept_name": "neuropathology",
      "kb_source": "mesh",
      "link_score": 0.0,
      "timestamp": null
    },
    {
      "text": "bronchopneumonia",
      "label": "DISEASE",
      "start_char": 205,
      "end_char": 221,
      "sentence_idx": 142,
      "concept_id": "UNKNOWN",
      "concept_name": "bronchopneumonia",
      "kb_source": "mesh",
      "link_score": 0.0,
      "timestamp": null
    },
    {
      "text": "Congestion",
      "label": "DISEASE",
      "start_char": 0,
      "end_char": 10,
      "sentence_idx": 144,
      "concept_id": "UNKNOWN",
      "concept_name": "Congestion",
      "kb_source": "mesh",
      "link_score": 0.0,
      "timestamp": null
    },
    {
      "text": "congestion.,STOMACH",
      "label": "DISEASE",
      "start_char": 62,
      "end_char": 81,
      "sentence_idx": 148,
      "concept_id": "UNKNOWN",
      "concept_name": "congestion.,STOMACH",
      "kb_source": "mesh",
      "link_score": 0.0,
      "timestamp": null
    },
    {
      "text": "nodular hyperplasia",
      "label": "DISEASE",
      "start_char": 124,
      "end_char": 143,
      "sentence_idx": 148,
      "concept_id": "UNKNOWN",
      "concept_name": "nodular hyperplasia",
      "kb_source": "mesh",
      "link_score": 0.0,
      "timestamp": null
    },
    {
      "text": "Centrilobular congestion",
      "label": "DISEASE",
      "start_char": 0,
      "end_char": 24,
      "sentence_idx": 149,
      "concept_id": "UNKNOWN",
      "concept_name": "Centrilobular congestion",
      "kb_source": "mesh",
      "link_score": 0.0,
      "timestamp": null
    },
    {
      "text": "steatosis",
      "label": "DISEASE",
      "start_char": 30,
      "end_char": 39,
      "sentence_idx": 149,
      "concept_id": "UNKNOWN",
      "concept_name": "steatosis",
      "kb_source": "mesh",
      "link_score": 0.0,
      "timestamp": null
    },
    {
      "text": "ARYEPIGLOTTIC",
      "label": "CHEMICAL",
      "start_char": 96,
      "end_char": 109,
      "sentence_idx": 151,
      "concept_id": "UNKNOWN",
      "concept_name": "ARYEPIGLOTTIC",
      "kb_source": "rxnorm",
      "link_score": 0.0,
      "timestamp": null
    }
  ],
  "relations": [],
  "temporal_expressions": []
}