{
  "metadata": {
    "source_file": "data\\raw\\txt\\mtsamples\\mtsamples_4745__heart_catheterization__ventriculography____angiography___4_.txt",
    "file_name": "mtsamples_4745__heart_catheterization__ventriculography____angiography___4_.txt",
    "file_type": ".txt",
    "file_size_bytes": 5478,
    "processed_at": "2026-05-09T09:54:44.104074"
  },
  "entities": [
    {
      "text": "NAME",
      "label": "CHEMICAL",
      "start_char": 0,
      "end_char": 4,
      "sentence_idx": 0,
      "concept_id": "UNKNOWN",
      "concept_name": "NAME",
      "kb_source": "rxnorm",
      "link_score": 0.0,
      "timestamp": null
    },
    {
      "text": "angioplasty",
      "label": "DISEASE",
      "start_char": 35,
      "end_char": 46,
      "sentence_idx": 2,
      "concept_id": "UNKNOWN",
      "concept_name": "angioplasty",
      "kb_source": "mesh",
      "link_score": 0.0,
      "timestamp": null
    },
    {
      "text": "myocardial infarction",
      "label": "DISEASE",
      "start_char": 62,
      "end_char": 83,
      "sentence_idx": 3,
      "concept_id": "UNKNOWN",
      "concept_name": "myocardial infarction",
      "kb_source": "mesh",
      "link_score": 0.0,
      "timestamp": null
    },
    {
      "text": "obstructive coronary artery disease",
      "label": "DISEASE",
      "start_char": 47,
      "end_char": 82,
      "sentence_idx": 4,
      "concept_id": "UNKNOWN",
      "concept_name": "obstructive coronary artery disease",
      "kb_source": "mesh",
      "link_score": 0.0,
      "timestamp": null
    },
    {
      "text": "Xylocaine",
      "label": "CHEMICAL",
      "start_char": 68,
      "end_char": 77,
      "sentence_idx": 6,
      "concept_id": "UNKNOWN",
      "concept_name": "Xylocaine",
      "kb_source": "rxnorm",
      "link_score": 0.0,
      "timestamp": null
    },
    {
      "text": "heparin",
      "label": "CHEMICAL",
      "start_char": 38,
      "end_char": 45,
      "sentence_idx": 8,
      "concept_id": "C0019134",
      "concept_name": "heparin",
      "kb_source": "rxnorm",
      "link_score": 0.9695241451263428,
      "timestamp": null
    },
    {
      "text": "Integrilin",
      "label": "CHEMICAL",
      "start_char": 0,
      "end_char": 10,
      "sentence_idx": 15,
      "concept_id": "C0950902",
      "concept_name": "Integrilin",
      "kb_source": "rxnorm",
      "link_score": 0.9600422382354736,
      "timestamp": null
    },
    {
      "text": "nitroglycerin",
      "label": "CHEMICAL",
      "start_char": 48,
      "end_char": 61,
      "sentence_idx": 20,
      "concept_id": "C0017887",
      "concept_name": "nitroglycerin",
      "kb_source": "rxnorm",
      "link_score": 0.9811209440231323,
      "timestamp": null
    },
    {
      "text": "anterolateral hypokinesis",
      "label": "DISEASE",
      "start_char": 16,
      "end_char": 41,
      "sentence_idx": 37,
      "concept_id": "UNKNOWN",
      "concept_name": "anterolateral hypokinesis",
      "kb_source": "mesh",
      "link_score": 0.0,
      "timestamp": null
    },
    {
      "text": "prolapse or regurgitation",
      "label": "DISEASE",
      "start_char": 36,
      "end_char": 61,
      "sentence_idx": 39,
      "concept_id": "UNKNOWN",
      "concept_name": "prolapse or regurgitation",
      "kb_source": "mesh",
      "link_score": 0.0,
      "timestamp": null
    },
    {
      "text": "aortic valve",
      "label": "DISEASE",
      "start_char": 4,
      "end_char": 16,
      "sentence_idx": 40,
      "concept_id": "UNKNOWN",
      "concept_name": "aortic valve",
      "kb_source": "mesh",
      "link_score": 0.0,
      "timestamp": null
    },
    {
      "text": "obstructive coronary artery disease",
      "label": "DISEASE",
      "start_char": 41,
      "end_char": 76,
      "sentence_idx": 43,
      "concept_id": "UNKNOWN",
      "concept_name": "obstructive coronary artery disease",
      "kb_source": "mesh",
      "link_score": 0.0,
      "timestamp": null
    },
    {
      "text": "high-grade disease",
      "label": "DISEASE",
      "start_char": 61,
      "end_char": 79,
      "sentence_idx": 47,
      "concept_id": "UNKNOWN",
      "concept_name": "high-grade disease",
      "kb_source": "mesh",
      "link_score": 0.0,
      "timestamp": null
    },
    {
      "text": "stenosis",
      "label": "DISEASE",
      "start_char": 30,
      "end_char": 38,
      "sentence_idx": 51,
      "concept_id": "UNKNOWN",
      "concept_name": "stenosis",
      "kb_source": "mesh",
      "link_score": 0.0,
      "timestamp": null
    },
    {
      "text": "high-grade disease",
      "label": "DISEASE",
      "start_char": 55,
      "end_char": 73,
      "sentence_idx": 52,
      "concept_id": "UNKNOWN",
      "concept_name": "high-grade disease",
      "kb_source": "mesh",
      "link_score": 0.0,
      "timestamp": null
    },
    {
      "text": "high-grade disease",
      "label": "DISEASE",
      "start_char": 110,
      "end_char": 128,
      "sentence_idx": 54,
      "concept_id": "UNKNOWN",
      "concept_name": "high-grade disease",
      "kb_source": "mesh",
      "link_score": 0.0,
      "timestamp": null
    },
    {
      "text": "stenosis",
      "label": "DISEASE",
      "start_char": 83,
      "end_char": 91,
      "sentence_idx": 55,
      "concept_id": "UNKNOWN",
      "concept_name": "stenosis",
      "kb_source": "mesh",
      "link_score": 0.0,
      "timestamp": null
    },
    {
      "text": "high-grade disease",
      "label": "DISEASE",
      "start_char": 56,
      "end_char": 74,
      "sentence_idx": 56,
      "concept_id": "UNKNOWN",
      "concept_name": "high-grade disease",
      "kb_source": "mesh",
      "link_score": 0.0,
      "timestamp": null
    },
    {
      "text": "angioplasty",
      "label": "DISEASE",
      "start_char": 40,
      "end_char": 51,
      "sentence_idx": 57,
      "concept_id": "UNKNOWN",
      "concept_name": "angioplasty",
      "kb_source": "mesh",
      "link_score": 0.0,
      "timestamp": null
    },
    {
      "text": "stenosis",
      "label": "DISEASE",
      "start_char": 108,
      "end_char": 116,
      "sentence_idx": 57,
      "concept_id": "UNKNOWN",
      "concept_name": "stenosis",
      "kb_source": "mesh",
      "link_score": 0.0,
      "timestamp": null
    },
    {
      "text": "stenosis",
      "label": "DISEASE",
      "start_char": 50,
      "end_char": 58,
      "sentence_idx": 58,
      "concept_id": "UNKNOWN",
      "concept_name": "stenosis",
      "kb_source": "mesh",
      "link_score": 0.0,
      "timestamp": null
    },
    {
      "text": "partial occlusion of the third posterolateral branch",
      "label": "DISEASE",
      "start_char": 79,
      "end_char": 131,
      "sentence_idx": 58,
      "concept_id": "UNKNOWN",
      "concept_name": "partial occlusion of the third posterolateral branch",
      "kb_source": "mesh",
      "link_score": 0.0,
      "timestamp": null
    },
    {
      "text": "angioplasty",
      "label": "DISEASE",
      "start_char": 37,
      "end_char": 48,
      "sentence_idx": 61,
      "concept_id": "UNKNOWN",
      "concept_name": "angioplasty",
      "kb_source": "mesh",
      "link_score": 0.0,
      "timestamp": null
    },
    {
      "text": "Thallium",
      "label": "CHEMICAL",
      "start_char": 0,
      "end_char": 8,
      "sentence_idx": 68,
      "concept_id": "C0039738",
      "concept_name": "thallium",
      "kb_source": "rxnorm",
      "link_score": 0.9765779376029968,
      "timestamp": null
    }
  ],
  "relations": [],
  "temporal_expressions": []
}