{
  "metadata": {
    "source_file": "data\\raw\\txt\\mtsamples\\mtsamples_2411__decreased_vision_consult_.txt",
    "file_name": "mtsamples_2411__decreased_vision_consult_.txt",
    "file_type": ".txt",
    "file_size_bytes": 3549,
    "processed_at": "2026-05-09T09:54:01.292377"
  },
  "entities": [
    {
      "text": "cataract",
      "label": "DISEASE",
      "start_char": 40,
      "end_char": 48,
      "sentence_idx": 0,
      "concept_id": "UNKNOWN",
      "concept_name": "cataract",
      "kb_source": "mesh",
      "link_score": 0.0,
      "timestamp": null
    },
    {
      "text": "lens",
      "label": "DISEASE",
      "start_char": 65,
      "end_char": 69,
      "sentence_idx": 0,
      "concept_id": "UNKNOWN",
      "concept_name": "lens",
      "kb_source": "mesh",
      "link_score": 0.0,
      "timestamp": null
    },
    {
      "text": "glaucoma",
      "label": "DISEASE",
      "start_char": 26,
      "end_char": 34,
      "sentence_idx": 1,
      "concept_id": "UNKNOWN",
      "concept_name": "glaucoma",
      "kb_source": "mesh",
      "link_score": 0.0,
      "timestamp": null
    },
    {
      "text": "today.,Her",
      "label": "CHEMICAL",
      "start_char": 78,
      "end_char": 88,
      "sentence_idx": 3,
      "concept_id": "UNKNOWN",
      "concept_name": "today.,Her",
      "kb_source": "rxnorm",
      "link_score": 0.0,
      "timestamp": null
    },
    {
      "text": "hypertension",
      "label": "DISEASE",
      "start_char": 119,
      "end_char": 131,
      "sentence_idx": 3,
      "concept_id": "UNKNOWN",
      "concept_name": "hypertension",
      "kb_source": "mesh",
      "link_score": 0.0,
      "timestamp": null
    },
    {
      "text": "hypercholesterolemia",
      "label": "DISEASE",
      "start_char": 136,
      "end_char": 156,
      "sentence_idx": 3,
      "concept_id": "UNKNOWN",
      "concept_name": "hypercholesterolemia",
      "kb_source": "mesh",
      "link_score": 0.0,
      "timestamp": null
    },
    {
      "text": "pilocarpine",
      "label": "CHEMICAL",
      "start_char": 253,
      "end_char": 264,
      "sentence_idx": 3,
      "concept_id": "C0031923",
      "concept_name": "pilocarpine",
      "kb_source": "rxnorm",
      "link_score": 0.9506012797355652,
      "timestamp": null
    },
    {
      "text": "Eltroxin",
      "label": "CHEMICAL",
      "start_char": 15,
      "end_char": 23,
      "sentence_idx": 5,
      "concept_id": "UNKNOWN",
      "concept_name": "Eltroxin",
      "kb_source": "rxnorm",
      "link_score": 0.0,
      "timestamp": null
    },
    {
      "text": "hypothyroidism",
      "label": "DISEASE",
      "start_char": 37,
      "end_char": 51,
      "sentence_idx": 5,
      "concept_id": "UNKNOWN",
      "concept_name": "hypothyroidism",
      "kb_source": "mesh",
      "link_score": 0.0,
      "timestamp": null
    },
    {
      "text": "Plendil",
      "label": "CHEMICAL",
      "start_char": 53,
      "end_char": 60,
      "sentence_idx": 5,
      "concept_id": "C0700021",
      "concept_name": "Plendil",
      "kb_source": "rxnorm",
      "link_score": 0.9835163950920105,
      "timestamp": null
    },
    {
      "text": "pravastatin.,She",
      "label": "CHEMICAL",
      "start_char": 85,
      "end_char": 101,
      "sentence_idx": 5,
      "concept_id": "C0085542",
      "concept_name": "pravastatin",
      "kb_source": "rxnorm",
      "link_score": 0.8788959980010986,
      "timestamp": null
    },
    {
      "text": "allergic",
      "label": "DISEASE",
      "start_char": 105,
      "end_char": 113,
      "sentence_idx": 5,
      "concept_id": "UNKNOWN",
      "concept_name": "allergic",
      "kb_source": "mesh",
      "link_score": 0.0,
      "timestamp": null
    },
    {
      "text": "blindness",
      "label": "DISEASE",
      "start_char": 153,
      "end_char": 162,
      "sentence_idx": 5,
      "concept_id": "UNKNOWN",
      "concept_name": "blindness",
      "kb_source": "mesh",
      "link_score": 0.0,
      "timestamp": null
    },
    {
      "text": "glaucoma",
      "label": "DISEASE",
      "start_char": 189,
      "end_char": 197,
      "sentence_idx": 5,
      "concept_id": "UNKNOWN",
      "concept_name": "glaucoma",
      "kb_source": "mesh",
      "link_score": 0.0,
      "timestamp": null
    },
    {
      "text": "hypertension.,Her",
      "label": "DISEASE",
      "start_char": 202,
      "end_char": 219,
      "sentence_idx": 5,
      "concept_id": "UNKNOWN",
      "concept_name": "hypertension.,Her",
      "kb_source": "mesh",
      "link_score": 0.0,
      "timestamp": null
    },
    {
      "text": "Manifest",
      "label": "DISEASE",
      "start_char": 0,
      "end_char": 8,
      "sentence_idx": 6,
      "concept_id": "UNKNOWN",
      "concept_name": "Manifest",
      "kb_source": "mesh",
      "link_score": 0.0,
      "timestamp": null
    },
    {
      "text": "dry eye",
      "label": "DISEASE",
      "start_char": 13,
      "end_char": 20,
      "sentence_idx": 11,
      "concept_id": "UNKNOWN",
      "concept_name": "dry eye",
      "kb_source": "mesh",
      "link_score": 0.0,
      "timestamp": null
    },
    {
      "text": "pallor",
      "label": "DISEASE",
      "start_char": 30,
      "end_char": 36,
      "sentence_idx": 17,
      "concept_id": "UNKNOWN",
      "concept_name": "pallor",
      "kb_source": "mesh",
      "link_score": 0.0,
      "timestamp": null
    },
    {
      "text": "glaucoma",
      "label": "DISEASE",
      "start_char": 21,
      "end_char": 29,
      "sentence_idx": 20,
      "concept_id": "UNKNOWN",
      "concept_name": "glaucoma",
      "kb_source": "mesh",
      "link_score": 0.0,
      "timestamp": null
    },
    {
      "text": "drusen",
      "label": "DISEASE",
      "start_char": 146,
      "end_char": 152,
      "sentence_idx": 20,
      "concept_id": "UNKNOWN",
      "concept_name": "drusen",
      "kb_source": "mesh",
      "link_score": 0.0,
      "timestamp": null
    },
    {
      "text": "RPE atrophy",
      "label": "DISEASE",
      "start_char": 173,
      "end_char": 184,
      "sentence_idx": 20,
      "concept_id": "UNKNOWN",
      "concept_name": "RPE atrophy",
      "kb_source": "mesh",
      "link_score": 0.0,
      "timestamp": null
    },
    {
      "text": "hemorrhage",
      "label": "DISEASE",
      "start_char": 83,
      "end_char": 93,
      "sentence_idx": 21,
      "concept_id": "UNKNOWN",
      "concept_name": "hemorrhage",
      "kb_source": "mesh",
      "link_score": 0.0,
      "timestamp": null
    },
    {
      "text": "RPE atrophy",
      "label": "DISEASE",
      "start_char": 33,
      "end_char": 44,
      "sentence_idx": 22,
      "concept_id": "UNKNOWN",
      "concept_name": "RPE atrophy",
      "kb_source": "mesh",
      "link_score": 0.0,
      "timestamp": null
    },
    {
      "text": "drusen",
      "label": "DISEASE",
      "start_char": 48,
      "end_char": 54,
      "sentence_idx": 23,
      "concept_id": "UNKNOWN",
      "concept_name": "drusen",
      "kb_source": "mesh",
      "link_score": 0.0,
      "timestamp": null
    },
    {
      "text": "RPE",
      "label": "DISEASE",
      "start_char": 4,
      "end_char": 7,
      "sentence_idx": 24,
      "concept_id": "UNKNOWN",
      "concept_name": "RPE",
      "kb_source": "mesh",
      "link_score": 0.0,
      "timestamp": null
    },
    {
      "text": "RPE atrophy",
      "label": "DISEASE",
      "start_char": 47,
      "end_char": 58,
      "sentence_idx": 25,
      "concept_id": "UNKNOWN",
      "concept_name": "RPE atrophy",
      "kb_source": "mesh",
      "link_score": 0.0,
      "timestamp": null
    },
    {
      "text": "glaucoma",
      "label": "DISEASE",
      "start_char": 8,
      "end_char": 16,
      "sentence_idx": 27,
      "concept_id": "UNKNOWN",
      "concept_name": "glaucoma",
      "kb_source": "mesh",
      "link_score": 0.0,
      "timestamp": null
    },
    {
      "text": "allergic reaction",
      "label": "DISEASE",
      "start_char": 8,
      "end_char": 25,
      "sentence_idx": 29,
      "concept_id": "UNKNOWN",
      "concept_name": "allergic reaction",
      "kb_source": "mesh",
      "link_score": 0.0,
      "timestamp": null
    },
    {
      "text": "Cosopt",
      "label": "CHEMICAL",
      "start_char": 29,
      "end_char": 35,
      "sentence_idx": 29,
      "concept_id": "C0719542",
      "concept_name": "Cosopt",
      "kb_source": "rxnorm",
      "link_score": 0.9852448105812073,
      "timestamp": null
    },
    {
      "text": "Xalatan",
      "label": "CHEMICAL",
      "start_char": 26,
      "end_char": 33,
      "sentence_idx": 30,
      "concept_id": "C0593887",
      "concept_name": "Xalatan",
      "kb_source": "rxnorm",
      "link_score": 0.9640992879867554,
      "timestamp": null
    },
    {
      "text": "vision",
      "label": "DISEASE",
      "start_char": 4,
      "end_char": 10,
      "sentence_idx": 33,
      "concept_id": "UNKNOWN",
      "concept_name": "vision",
      "kb_source": "mesh",
      "link_score": 0.0,
      "timestamp": null
    },
    {
      "text": "RPE atrophy",
      "label": "DISEASE",
      "start_char": 81,
      "end_char": 92,
      "sentence_idx": 33,
      "concept_id": "UNKNOWN",
      "concept_name": "RPE atrophy",
      "kb_source": "mesh",
      "link_score": 0.0,
      "timestamp": null
    }
  ],
  "relations": [],
  "temporal_expressions": []
}