{
  "metadata": {
    "source_file": "data\\raw\\txt\\mtsamples\\mtsamples_3779__acquired_hypothyroidism_followup_.txt",
    "file_name": "mtsamples_3779__acquired_hypothyroidism_followup_.txt",
    "file_type": ".txt",
    "file_size_bytes": 3288,
    "processed_at": "2026-05-09T09:54:27.369273"
  },
  "entities": [
    {
      "text": "LIST:,1",
      "label": "CHEMICAL",
      "start_char": 8,
      "end_char": 15,
      "sentence_idx": 0,
      "concept_id": "UNKNOWN",
      "concept_name": "LIST:,1",
      "kb_source": "rxnorm",
      "link_score": 0.0,
      "timestamp": "2025-11-10"
    },
    {
      "text": "Papillary carcinoma of the thyroid",
      "label": "DISEASE",
      "start_char": 0,
      "end_char": 34,
      "sentence_idx": 2,
      "concept_id": "UNKNOWN",
      "concept_name": "Papillary carcinoma of the thyroid",
      "kb_source": "mesh",
      "link_score": 0.0,
      "timestamp": "2025-11-10"
    },
    {
      "text": "Diabetes mellitus.,4",
      "label": "DISEASE",
      "start_char": 0,
      "end_char": 20,
      "sentence_idx": 3,
      "concept_id": "UNKNOWN",
      "concept_name": "Diabetes mellitus.,4",
      "kb_source": "mesh",
      "link_score": 0.0,
      "timestamp": "2025-11-10"
    },
    {
      "text": "Insomnia",
      "label": "DISEASE",
      "start_char": 0,
      "end_char": 8,
      "sentence_idx": 4,
      "concept_id": "UNKNOWN",
      "concept_name": "Insomnia",
      "kb_source": "mesh",
      "link_score": 0.0,
      "timestamp": "2025-11-10"
    },
    {
      "text": "primary complaint",
      "label": "DISEASE",
      "start_char": 11,
      "end_char": 28,
      "sentence_idx": 8,
      "concept_id": "UNKNOWN",
      "concept_name": "primary complaint",
      "kb_source": "mesh",
      "link_score": 0.0,
      "timestamp": "2025-11-10"
    },
    {
      "text": "fatigue",
      "label": "DISEASE",
      "start_char": 39,
      "end_char": 46,
      "sentence_idx": 8,
      "concept_id": "UNKNOWN",
      "concept_name": "fatigue",
      "kb_source": "mesh",
      "link_score": 0.0,
      "timestamp": "2025-11-10"
    },
    {
      "text": "hypothyroidism",
      "label": "DISEASE",
      "start_char": 113,
      "end_char": 127,
      "sentence_idx": 10,
      "concept_id": "UNKNOWN",
      "concept_name": "hypothyroidism",
      "kb_source": "mesh",
      "link_score": 0.0,
      "timestamp": "2025-11-10"
    },
    {
      "text": "palpitations",
      "label": "DISEASE",
      "start_char": 46,
      "end_char": 58,
      "sentence_idx": 11,
      "concept_id": "UNKNOWN",
      "concept_name": "palpitations",
      "kb_source": "mesh",
      "link_score": 0.0,
      "timestamp": "2025-11-10"
    },
    {
      "text": "muscle weakness",
      "label": "DISEASE",
      "start_char": 60,
      "end_char": 75,
      "sentence_idx": 11,
      "concept_id": "UNKNOWN",
      "concept_name": "muscle weakness",
      "kb_source": "mesh",
      "link_score": 0.0,
      "timestamp": "2025-11-10"
    },
    {
      "text": "tremors",
      "label": "DISEASE",
      "start_char": 77,
      "end_char": 84,
      "sentence_idx": 11,
      "concept_id": "UNKNOWN",
      "concept_name": "tremors",
      "kb_source": "mesh",
      "link_score": 0.0,
      "timestamp": "2025-11-10"
    },
    {
      "text": "nausea,",
      "label": "DISEASE",
      "start_char": 86,
      "end_char": 93,
      "sentence_idx": 11,
      "concept_id": "UNKNOWN",
      "concept_name": "nausea,",
      "kb_source": "mesh",
      "link_score": 0.0,
      "timestamp": "2025-11-10"
    },
    {
      "text": "constipation",
      "label": "DISEASE",
      "start_char": 104,
      "end_char": 116,
      "sentence_idx": 11,
      "concept_id": "UNKNOWN",
      "concept_name": "constipation",
      "kb_source": "mesh",
      "link_score": 0.0,
      "timestamp": "2025-11-10"
    },
    {
      "text": "diarrhea",
      "label": "DISEASE",
      "start_char": 137,
      "end_char": 145,
      "sentence_idx": 11,
      "concept_id": "UNKNOWN",
      "concept_name": "diarrhea",
      "kb_source": "mesh",
      "link_score": 0.0,
      "timestamp": "2025-11-10"
    },
    {
      "text": "Levothyroxine",
      "label": "CHEMICAL",
      "start_char": 0,
      "end_char": 13,
      "sentence_idx": 14,
      "concept_id": "C0040165",
      "concept_name": "levothyroxine",
      "kb_source": "rxnorm",
      "link_score": 0.9681282639503479,
      "timestamp": "2025-11-10"
    },
    {
      "text": "p.o",
      "label": "CHEMICAL",
      "start_char": 29,
      "end_char": 32,
      "sentence_idx": 14,
      "concept_id": "UNKNOWN",
      "concept_name": "p.o",
      "kb_source": "rxnorm",
      "link_score": 0.0,
      "timestamp": "2025-11-10"
    },
    {
      "text": "Byetta",
      "label": "CHEMICAL",
      "start_char": 0,
      "end_char": 6,
      "sentence_idx": 19,
      "concept_id": "C1636686",
      "concept_name": "Byetta",
      "kb_source": "rxnorm",
      "link_score": 0.983971893787384,
      "timestamp": "2025-11-10"
    },
    {
      "text": "polyuria",
      "label": "DISEASE",
      "start_char": 21,
      "end_char": 29,
      "sentence_idx": 20,
      "concept_id": "UNKNOWN",
      "concept_name": "polyuria",
      "kb_source": "mesh",
      "link_score": 0.0,
      "timestamp": "2025-11-10"
    },
    {
      "text": "polydipsia",
      "label": "DISEASE",
      "start_char": 31,
      "end_char": 41,
      "sentence_idx": 20,
      "concept_id": "UNKNOWN",
      "concept_name": "polydipsia",
      "kb_source": "mesh",
      "link_score": 0.0,
      "timestamp": "2025-11-10"
    },
    {
      "text": "polyphagia",
      "label": "DISEASE",
      "start_char": 45,
      "end_char": 55,
      "sentence_idx": 20,
      "concept_id": "UNKNOWN",
      "concept_name": "polyphagia",
      "kb_source": "mesh",
      "link_score": 0.0,
      "timestamp": "2025-11-10"
    },
    {
      "text": "chills",
      "label": "DISEASE",
      "start_char": 29,
      "end_char": 35,
      "sentence_idx": 21,
      "concept_id": "UNKNOWN",
      "concept_name": "chills",
      "kb_source": "mesh",
      "link_score": 0.0,
      "timestamp": "2025-11-10"
    },
    {
      "text": "sweats",
      "label": "DISEASE",
      "start_char": 37,
      "end_char": 43,
      "sentence_idx": 21,
      "concept_id": "UNKNOWN",
      "concept_name": "sweats",
      "kb_source": "mesh",
      "link_score": 0.0,
      "timestamp": "2025-11-10"
    },
    {
      "text": "nausea,",
      "label": "DISEASE",
      "start_char": 68,
      "end_char": 75,
      "sentence_idx": 21,
      "concept_id": "UNKNOWN",
      "concept_name": "nausea,",
      "kb_source": "mesh",
      "link_score": 0.0,
      "timestamp": "2025-11-10"
    },
    {
      "text": "constipation",
      "label": "DISEASE",
      "start_char": 86,
      "end_char": 98,
      "sentence_idx": 21,
      "concept_id": "UNKNOWN",
      "concept_name": "constipation",
      "kb_source": "mesh",
      "link_score": 0.0,
      "timestamp": "2025-11-10"
    },
    {
      "text": "diarrhea",
      "label": "DISEASE",
      "start_char": 102,
      "end_char": 110,
      "sentence_idx": 21,
      "concept_id": "UNKNOWN",
      "concept_name": "diarrhea",
      "kb_source": "mesh",
      "link_score": 0.0,
      "timestamp": "2025-11-10"
    },
    {
      "text": "lightheadedness, weakness",
      "label": "DISEASE",
      "start_char": 22,
      "end_char": 47,
      "sentence_idx": 22,
      "concept_id": "UNKNOWN",
      "concept_name": "lightheadedness, weakness",
      "kb_source": "mesh",
      "link_score": 0.0,
      "timestamp": "2025-11-10"
    },
    {
      "text": "chest pain",
      "label": "DISEASE",
      "start_char": 49,
      "end_char": 59,
      "sentence_idx": 22,
      "concept_id": "UNKNOWN",
      "concept_name": "chest pain",
      "kb_source": "mesh",
      "link_score": 0.0,
      "timestamp": "2025-11-10"
    },
    {
      "text": "shortness of breath",
      "label": "DISEASE",
      "start_char": 61,
      "end_char": 80,
      "sentence_idx": 22,
      "concept_id": "UNKNOWN",
      "concept_name": "shortness of breath",
      "kb_source": "mesh",
      "link_score": 0.0,
      "timestamp": "2025-11-10"
    },
    {
      "text": "orthopnea",
      "label": "DISEASE",
      "start_char": 104,
      "end_char": 113,
      "sentence_idx": 22,
      "concept_id": "UNKNOWN",
      "concept_name": "orthopnea",
      "kb_source": "mesh",
      "link_score": 0.0,
      "timestamp": "2025-11-10"
    },
    {
      "text": "dyspnea",
      "label": "DISEASE",
      "start_char": 117,
      "end_char": 124,
      "sentence_idx": 22,
      "concept_id": "UNKNOWN",
      "concept_name": "dyspnea",
      "kb_source": "mesh",
      "link_score": 0.0,
      "timestamp": "2025-11-10"
    },
    {
      "text": "lymphadenopathy",
      "label": "DISEASE",
      "start_char": 12,
      "end_char": 27,
      "sentence_idx": 26,
      "concept_id": "UNKNOWN",
      "concept_name": "lymphadenopathy",
      "kb_source": "mesh",
      "link_score": 0.0,
      "timestamp": "2025-11-10"
    },
    {
      "text": "tremor",
      "label": "DISEASE",
      "start_char": 16,
      "end_char": 22,
      "sentence_idx": 32,
      "concept_id": "UNKNOWN",
      "concept_name": "tremor",
      "kb_source": "mesh",
      "link_score": 0.0,
      "timestamp": "2025-11-10"
    },
    {
      "text": "PLAN:,This",
      "label": "DISEASE",
      "start_char": 251,
      "end_char": 261,
      "sentence_idx": 33,
      "concept_id": "UNKNOWN",
      "concept_name": "PLAN:,This",
      "kb_source": "mesh",
      "link_score": 0.0,
      "timestamp": "2025-11-10"
    },
    {
      "text": "hypothyroidism",
      "label": "DISEASE",
      "start_char": 9,
      "end_char": 23,
      "sentence_idx": 34,
      "concept_id": "UNKNOWN",
      "concept_name": "hypothyroidism",
      "kb_source": "mesh",
      "link_score": 0.0,
      "timestamp": "2025-11-10"
    },
    {
      "text": "papillary carcinoma",
      "label": "DISEASE",
      "start_char": 61,
      "end_char": 80,
      "sentence_idx": 34,
      "concept_id": "UNKNOWN",
      "concept_name": "papillary carcinoma",
      "kb_source": "mesh",
      "link_score": 0.0,
      "timestamp": "2025-11-10"
    },
    {
      "text": "hypothyroid",
      "label": "DISEASE",
      "start_char": 88,
      "end_char": 99,
      "sentence_idx": 37,
      "concept_id": "UNKNOWN",
      "concept_name": "hypothyroid",
      "kb_source": "mesh",
      "link_score": 0.0,
      "timestamp": "2025-11-10"
    }
  ],
  "relations": [],
  "temporal_expressions": [
    {
      "raw_text": "08/29/07",
      "start_char": 2282,
      "end_char": 2290
    },
    {
      "raw_text": "6 months ago",
      "start_char": 348,
      "end_char": 360
    }
  ]
}