{
  "metadata": {
    "source_file": "data\\raw\\txt\\mtsamples\\mtsamples_3681__sinus_problems___consult_.txt",
    "file_name": "mtsamples_3681__sinus_problems___consult_.txt",
    "file_type": ".txt",
    "file_size_bytes": 2242,
    "processed_at": "2026-05-09T09:54:26.095794"
  },
  "entities": [
    {
      "text": "postnasal",
      "label": "DISEASE",
      "start_char": 17,
      "end_char": 26,
      "sentence_idx": 1,
      "concept_id": "UNKNOWN",
      "concept_name": "postnasal",
      "kb_source": "mesh",
      "link_score": 0.0,
      "timestamp": "2026-04-26"
    },
    {
      "text": "sore throat",
      "label": "DISEASE",
      "start_char": 37,
      "end_char": 48,
      "sentence_idx": 1,
      "concept_id": "UNKNOWN",
      "concept_name": "sore throat",
      "kb_source": "mesh",
      "link_score": 0.0,
      "timestamp": "2026-04-26"
    },
    {
      "text": "pain",
      "label": "DISEASE",
      "start_char": 57,
      "end_char": 61,
      "sentence_idx": 1,
      "concept_id": "C0030346",
      "concept_name": "Papain",
      "kb_source": "mesh",
      "link_score": 0.7236586213111877,
      "timestamp": "2026-04-26"
    },
    {
      "text": "headaches",
      "label": "DISEASE",
      "start_char": 73,
      "end_char": 82,
      "sentence_idx": 1,
      "concept_id": "UNKNOWN",
      "concept_name": "headaches",
      "kb_source": "mesh",
      "link_score": 0.0,
      "timestamp": "2026-04-26"
    },
    {
      "text": "congestion",
      "label": "DISEASE",
      "start_char": 87,
      "end_char": 97,
      "sentence_idx": 1,
      "concept_id": "UNKNOWN",
      "concept_name": "congestion",
      "kb_source": "mesh",
      "link_score": 0.0,
      "timestamp": "2026-04-26"
    },
    {
      "text": "snoring",
      "label": "DISEASE",
      "start_char": 28,
      "end_char": 35,
      "sentence_idx": 2,
      "concept_id": "UNKNOWN",
      "concept_name": "snoring",
      "kb_source": "mesh",
      "link_score": 0.0,
      "timestamp": "2026-04-26"
    },
    {
      "text": "nasal burning",
      "label": "DISEASE",
      "start_char": 37,
      "end_char": 50,
      "sentence_idx": 2,
      "concept_id": "UNKNOWN",
      "concept_name": "nasal burning",
      "kb_source": "mesh",
      "link_score": 0.0,
      "timestamp": "2026-04-26"
    },
    {
      "text": "teeth pain",
      "label": "DISEASE",
      "start_char": 55,
      "end_char": 65,
      "sentence_idx": 2,
      "concept_id": "UNKNOWN",
      "concept_name": "teeth pain",
      "kb_source": "mesh",
      "link_score": 0.0,
      "timestamp": "2026-04-26"
    },
    {
      "text": "SYSTEMS:,ROS",
      "label": "DISEASE",
      "start_char": 57,
      "end_char": 69,
      "sentence_idx": 4,
      "concept_id": "UNKNOWN",
      "concept_name": "SYSTEMS:,ROS",
      "kb_source": "mesh",
      "link_score": 0.0,
      "timestamp": "2026-04-26"
    },
    {
      "text": "respiratory complaints",
      "label": "DISEASE",
      "start_char": 201,
      "end_char": 223,
      "sentence_idx": 4,
      "concept_id": "UNKNOWN",
      "concept_name": "respiratory complaints",
      "kb_source": "mesh",
      "link_score": 0.0,
      "timestamp": "2026-04-26"
    },
    {
      "text": "cough",
      "label": "DISEASE",
      "start_char": 233,
      "end_char": 238,
      "sentence_idx": 4,
      "concept_id": "UNKNOWN",
      "concept_name": "cough",
      "kb_source": "mesh",
      "link_score": 0.0,
      "timestamp": "2026-04-26"
    },
    {
      "text": "shortness of breath",
      "label": "DISEASE",
      "start_char": 240,
      "end_char": 259,
      "sentence_idx": 4,
      "concept_id": "UNKNOWN",
      "concept_name": "shortness of breath",
      "kb_source": "mesh",
      "link_score": 0.0,
      "timestamp": "2026-04-26"
    },
    {
      "text": "chest pain",
      "label": "DISEASE",
      "start_char": 261,
      "end_char": 271,
      "sentence_idx": 4,
      "concept_id": "UNKNOWN",
      "concept_name": "chest pain",
      "kb_source": "mesh",
      "link_score": 0.0,
      "timestamp": "2026-04-26"
    },
    {
      "text": "wheezing",
      "label": "DISEASE",
      "start_char": 273,
      "end_char": 281,
      "sentence_idx": 4,
      "concept_id": "UNKNOWN",
      "concept_name": "wheezing",
      "kb_source": "mesh",
      "link_score": 0.0,
      "timestamp": "2026-04-26"
    },
    {
      "text": "hemoptysis",
      "label": "DISEASE",
      "start_char": 283,
      "end_char": 293,
      "sentence_idx": 4,
      "concept_id": "UNKNOWN",
      "concept_name": "hemoptysis",
      "kb_source": "mesh",
      "link_score": 0.0,
      "timestamp": "2026-04-26"
    },
    {
      "text": "etc.,ROS",
      "label": "DISEASE",
      "start_char": 295,
      "end_char": 303,
      "sentence_idx": 4,
      "concept_id": "UNKNOWN",
      "concept_name": "etc.,ROS",
      "kb_source": "mesh",
      "link_score": 0.0,
      "timestamp": "2026-04-26"
    },
    {
      "text": "nausea, vomiting",
      "label": "DISEASE",
      "start_char": 341,
      "end_char": 357,
      "sentence_idx": 4,
      "concept_id": "UNKNOWN",
      "concept_name": "nausea, vomiting",
      "kb_source": "mesh",
      "link_score": 0.0,
      "timestamp": "2026-04-26"
    },
    {
      "text": "abdominal pain",
      "label": "DISEASE",
      "start_char": 359,
      "end_char": 373,
      "sentence_idx": 4,
      "concept_id": "UNKNOWN",
      "concept_name": "abdominal pain",
      "kb_source": "mesh",
      "link_score": 0.0,
      "timestamp": "2026-04-26"
    },
    {
      "text": "dysphagia",
      "label": "DISEASE",
      "start_char": 375,
      "end_char": 384,
      "sentence_idx": 4,
      "concept_id": "UNKNOWN",
      "concept_name": "dysphagia",
      "kb_source": "mesh",
      "link_score": 0.0,
      "timestamp": "2026-04-26"
    },
    {
      "text": "headaches",
      "label": "DISEASE",
      "start_char": 502,
      "end_char": 511,
      "sentence_idx": 4,
      "concept_id": "UNKNOWN",
      "concept_name": "headaches",
      "kb_source": "mesh",
      "link_score": 0.0,
      "timestamp": "2026-04-26"
    },
    {
      "text": "negative.,PAST",
      "label": "CHEMICAL",
      "start_char": 22,
      "end_char": 36,
      "sentence_idx": 5,
      "concept_id": "UNKNOWN",
      "concept_name": "negative.,PAST",
      "kb_source": "rxnorm",
      "link_score": 0.0,
      "timestamp": "2026-04-26"
    },
    {
      "text": "Negative.,PAST",
      "label": "DISEASE",
      "start_char": 35,
      "end_char": 49,
      "sentence_idx": 6,
      "concept_id": "UNKNOWN",
      "concept_name": "Negative.,PAST",
      "kb_source": "mesh",
      "link_score": 0.0,
      "timestamp": "2026-04-26"
    },
    {
      "text": "alcohol",
      "label": "CHEMICAL",
      "start_char": 18,
      "end_char": 25,
      "sentence_idx": 7,
      "concept_id": "C0001963",
      "concept_name": "methyl alcohol",
      "kb_source": "rxnorm",
      "link_score": 0.7954661846160889,
      "timestamp": "2026-04-26"
    },
    {
      "text": "allergies",
      "label": "DISEASE",
      "start_char": 81,
      "end_char": 90,
      "sentence_idx": 9,
      "concept_id": "UNKNOWN",
      "concept_name": "allergies",
      "kb_source": "mesh",
      "link_score": 0.0,
      "timestamp": "2026-04-26"
    },
    {
      "text": "Claritin",
      "label": "CHEMICAL",
      "start_char": 131,
      "end_char": 139,
      "sentence_idx": 9,
      "concept_id": "C0701055",
      "concept_name": "Claritin",
      "kb_source": "rxnorm",
      "link_score": 0.9775713682174683,
      "timestamp": "2026-04-26"
    },
    {
      "text": "Rhinocort",
      "label": "CHEMICAL",
      "start_char": 42,
      "end_char": 51,
      "sentence_idx": 10,
      "concept_id": "C0678163",
      "concept_name": "Rhinocort",
      "kb_source": "rxnorm",
      "link_score": 0.981652557849884,
      "timestamp": "2026-04-26"
    },
    {
      "text": "Auricles/external auditory",
      "label": "DISEASE",
      "start_char": 81,
      "end_char": 107,
      "sentence_idx": 10,
      "concept_id": "UNKNOWN",
      "concept_name": "Auricles/external auditory",
      "kb_source": "mesh",
      "link_score": 0.0,
      "timestamp": "2026-04-26"
    },
    {
      "text": "effusion",
      "label": "DISEASE",
      "start_char": 30,
      "end_char": 38,
      "sentence_idx": 11,
      "concept_id": "UNKNOWN",
      "concept_name": "effusion",
      "kb_source": "mesh",
      "link_score": 0.0,
      "timestamp": "2026-04-26"
    },
    {
      "text": "congestion",
      "label": "DISEASE",
      "start_char": 115,
      "end_char": 125,
      "sentence_idx": 11,
      "concept_id": "UNKNOWN",
      "concept_name": "congestion",
      "kb_source": "mesh",
      "link_score": 0.0,
      "timestamp": "2026-04-26"
    },
    {
      "text": "purulent",
      "label": "DISEASE",
      "start_char": 130,
      "end_char": 138,
      "sentence_idx": 11,
      "concept_id": "UNKNOWN",
      "concept_name": "purulent",
      "kb_source": "mesh",
      "link_score": 0.0,
      "timestamp": "2026-04-26"
    },
    {
      "text": "purulent postnasal",
      "label": "DISEASE",
      "start_char": 67,
      "end_char": 85,
      "sentence_idx": 12,
      "concept_id": "UNKNOWN",
      "concept_name": "purulent postnasal",
      "kb_source": "mesh",
      "link_score": 0.0,
      "timestamp": "2026-04-26"
    },
    {
      "text": "tenderness",
      "label": "DISEASE",
      "start_char": 90,
      "end_char": 100,
      "sentence_idx": 13,
      "concept_id": "UNKNOWN",
      "concept_name": "tenderness",
      "kb_source": "mesh",
      "link_score": 0.0,
      "timestamp": "2026-04-26"
    },
    {
      "text": "tenderness",
      "label": "DISEASE",
      "start_char": 47,
      "end_char": 57,
      "sentence_idx": 14,
      "concept_id": "UNKNOWN",
      "concept_name": "tenderness",
      "kb_source": "mesh",
      "link_score": 0.0,
      "timestamp": "2026-04-26"
    },
    {
      "text": "maxillary sinus tenderness",
      "label": "DISEASE",
      "start_char": 132,
      "end_char": 158,
      "sentence_idx": 14,
      "concept_id": "UNKNOWN",
      "concept_name": "maxillary sinus tenderness",
      "kb_source": "mesh",
      "link_score": 0.0,
      "timestamp": "2026-04-26"
    },
    {
      "text": "Acute maxillary sinusitis",
      "label": "DISEASE",
      "start_char": 276,
      "end_char": 301,
      "sentence_idx": 14,
      "concept_id": "UNKNOWN",
      "concept_name": "Acute maxillary sinusitis",
      "kb_source": "mesh",
      "link_score": 0.0,
      "timestamp": "2026-04-26"
    },
    {
      "text": "Snoring",
      "label": "DISEASE",
      "start_char": 0,
      "end_char": 7,
      "sentence_idx": 15,
      "concept_id": "UNKNOWN",
      "concept_name": "Snoring",
      "kb_source": "mesh",
      "link_score": 0.0,
      "timestamp": "2026-04-26"
    },
    {
      "text": "Augmentin",
      "label": "CHEMICAL",
      "start_char": 31,
      "end_char": 40,
      "sentence_idx": 15,
      "concept_id": "UNKNOWN",
      "concept_name": "Augmentin",
      "kb_source": "rxnorm",
      "link_score": 0.0,
      "timestamp": "2026-04-26"
    }
  ],
  "relations": [],
  "temporal_expressions": [
    {
      "raw_text": "2 weeks ago",
      "start_char": 72,
      "end_char": 83
    }
  ]
}